{"generated": "2026-06-05T17:35:31Z", "cars": [{"id": 12895, "status": "active", "price": 55000, "ends_at": "2026-06-05T17:51:00Z", "dealer": "Bring a Trailer", "fmv": 73000, "fmv_low": 58920, "fmv_high": 93000, "conf": "HIGH"}, {"id": 12896, "status": "active", "price": 46525, "ends_at": "2026-06-05T17:44:59Z", "dealer": "Cars and Bids", "fmv": 54000, "fmv_low": 41000, "fmv_high": 69500, "conf": "HIGH"}, {"id": 12904, "status": "active", "price": 61500, "ends_at": "2026-06-05T18:18:00Z", "dealer": "Bring a Trailer", "fmv": 70000, "fmv_low": 68000, "fmv_high": 83987, "conf": "HIGH"}, {"id": 12905, "status": "active", "price": 46250, "ends_at": "2026-06-05T18:59:59Z", "dealer": "Cars and Bids", "fmv": 65000, "fmv_low": 53000, "fmv_high": 80996, "conf": "HIGH"}, {"id": 12906, "status": "active", "price": 102992, "ends_at": "2026-06-05T19:32:00Z", "dealer": "Bring a Trailer", "fmv": 0, "fmv_low": 0, "fmv_high": 0, "conf": "NONE"}, {"id": 13173, "status": "active", "price": 55000, "ends_at": "2026-06-05T18:59:13Z", "dealer": "pcarmarket", "fmv": 82500, "fmv_low": 71000, "fmv_high": 87067, "conf": "HIGH"}, {"id": 13174, "status": "active", "price": 33000, "ends_at": "2026-06-05T18:49:13Z", "dealer": "pcarmarket", "fmv": 65000, "fmv_low": 53500, "fmv_high": 80996, "conf": "HIGH"}, {"id": 13285, "status": "active", "price": 57800, "ends_at": "2026-06-06T17:05:00Z", "dealer": "Bring a Trailer", "fmv": 85599, "fmv_low": 66500, "fmv_high": 102000, "conf": "HIGH"}, {"id": 13514, "status": "active", "price": 48250, "ends_at": "2026-06-06T17:32:00Z", "dealer": "Bring a Trailer", "fmv": 73000, "fmv_low": 58920, "fmv_high": 93000, "conf": "HIGH"}, {"id": 13515, "status": "active", "price": 5500, "ends_at": "2026-06-06T18:34:00Z", "dealer": "Bring a Trailer", "fmv": 27500, "fmv_low": 22000, "fmv_high": 33750, "conf": "HIGH"}, {"id": 13516, "status": "active", "price": 98500, "ends_at": "2026-06-08T17:54:00Z", "dealer": "Bring a Trailer", "fmv": 97500, "fmv_low": 90500, "fmv_high": 104000, "conf": "HIGH"}, {"id": 13528, "status": "active", "price": 8647, "ends_at": "2026-06-08T17:34:07Z", "dealer": "Cars and Bids", "fmv": 14000, "fmv_low": 11400, "fmv_high": 17000, "conf": "MEDIUM"}, {"id": 13529, "status": "active", "price": 170000, "ends_at": "2026-06-08T18:13:00Z", "dealer": "Bring a Trailer", "fmv": 207000, "fmv_low": 195000, "fmv_high": 225000, "conf": "HIGH"}, {"id": 13541, "status": "active", "price": 2750, "ends_at": "2026-06-08T17:34:07Z", "dealer": "Cars and Bids", "fmv": 27500, "fmv_low": 22000, "fmv_high": 33750, "conf": "HIGH"}, {"id": 13545, "status": "active", "price": 48750, "ends_at": "2026-06-08T17:34:07Z", "dealer": "Cars and Bids", "fmv": 54000, "fmv_low": 41000, "fmv_high": 69500, "conf": "HIGH"}, {"id": 13546, "status": "active", "price": 12345, "ends_at": "2026-06-08T18:42:00Z", "dealer": "Bring a Trailer", "fmv": 25500, "fmv_low": 22500, "fmv_high": 30250, "conf": "MEDIUM"}, {"id": 13547, "status": "active", "price": 5000, "ends_at": "2026-06-08T18:59:13Z", "dealer": "pcarmarket", "fmv": 27169, "fmv_low": 22500, "fmv_high": 33000, "conf": "HIGH"}, {"id": 13553, "status": "active", "price": 34250, "ends_at": "2026-06-08T19:09:13Z", "dealer": "pcarmarket", "fmv": 39420, "fmv_low": 32000, "fmv_high": 49000, "conf": "HIGH"}, {"id": 13632, "status": "active", "price": 76500, "ends_at": "2026-06-09T18:53:00Z", "dealer": "Bring a Trailer", "fmv": 85003, "fmv_low": 76000, "fmv_high": 97000, "conf": "HIGH"}, {"id": 13644, "status": "active", "price": 52500, "ends_at": "2026-06-08T18:33:00Z", "dealer": "Bring a Trailer", "fmv": 78500, "fmv_low": 72000, "fmv_high": 91000, "conf": "HIGH"}, {"id": 13647, "status": "active", "price": 19911, "ends_at": "2026-06-06T17:21:00Z", "dealer": "Bring a Trailer", "fmv": 27750, "fmv_low": 22000, "fmv_high": 34000, "conf": "HIGH"}, {"id": 13649, "status": "active", "price": 711000, "ends_at": "2026-06-10T19:30:00Z", "dealer": "Bring a Trailer", "fmv": 463000, "fmv_low": 395000, "fmv_high": 560000, "conf": "HIGH"}, {"id": 13667, "status": "active", "price": 22250, "ends_at": "2026-06-09T17:34:07Z", "dealer": "Cars and Bids", "fmv": 96000, "fmv_low": 80500, "fmv_high": 129333, "conf": "HIGH"}, {"id": 13668, "status": "active", "price": 32000, "ends_at": "2026-06-09T18:49:17Z", "dealer": "pcarmarket", "fmv": 67000, "fmv_low": 62750, "fmv_high": 85000, "conf": "HIGH"}, {"id": 13670, "status": "active", "price": 90000, "ends_at": "2026-06-09T18:59:17Z", "dealer": "pcarmarket", "fmv": 123000, "fmv_low": 112000, "fmv_high": 128911, "conf": "HIGH"}, {"id": 13674, "status": "active", "price": 9987, "ends_at": "2026-06-09T17:34:07Z", "dealer": "Cars and Bids", "fmv": 29500, "fmv_low": 24000, "fmv_high": 40000, "conf": "MEDIUM"}, {"id": 13679, "status": "active", "price": 20000, "ends_at": "2026-06-09T18:39:17Z", "dealer": "pcarmarket", "fmv": 45750, "fmv_low": 44500, "fmv_high": 46750, "conf": "HIGH"}, {"id": 13684, "status": "active", "price": 715000, "ends_at": "2026-06-11T17:05:00Z", "dealer": "Bring a Trailer", "fmv": 0, "fmv_low": 0, "fmv_high": 0, "conf": "NONE"}, {"id": 13767, "status": "active", "price": 50500, "ends_at": "2026-06-10T17:50:00Z", "dealer": "Bring a Trailer", "fmv": 0, "fmv_low": 0, "fmv_high": 0, "conf": "NONE"}, {"id": 13770, "status": "active", "price": 9500, "ends_at": "2026-06-10T17:34:07Z", "dealer": "Cars and Bids", "fmv": 40751, "fmv_low": 30500, "fmv_high": 47500, "conf": "HIGH"}, {"id": 13775, "status": "active", "price": 25500, "ends_at": "2026-06-09T20:28:00Z", "dealer": "Bring a Trailer", "fmv": 40000, "fmv_low": 30500, "fmv_high": 47500, "conf": "HIGH"}, {"id": 13776, "status": "active", "price": 25000, "ends_at": "2026-06-09T21:00:00Z", "dealer": "Bring a Trailer", "fmv": 27750, "fmv_low": 22000, "fmv_high": 34000, "conf": "HIGH"}, {"id": 13781, "status": "active", "price": 4000, "ends_at": "2026-06-10T17:34:07Z", "dealer": "Cars and Bids", "fmv": 14000, "fmv_low": 11400, "fmv_high": 17000, "conf": "MEDIUM"}, {"id": 13782, "status": "active", "price": 71000, "ends_at": "2026-06-06T17:19:00Z", "dealer": "Bring a Trailer", "fmv": 123000, "fmv_low": 112000, "fmv_high": 128911, "conf": "HIGH"}, {"id": 13783, "status": "active", "price": 355000, "ends_at": "2026-06-08T17:10:00Z", "dealer": "Bring a Trailer", "fmv": 648000, "fmv_low": 625000, "fmv_high": 656000, "conf": "HIGH"}, {"id": 13789, "status": "active", "price": 250000, "ends_at": "2026-06-06T17:53:00Z", "dealer": "Bring a Trailer", "fmv": 277000, "fmv_low": 260000, "fmv_high": 305000, "conf": "HIGH"}, {"id": 13790, "status": "active", "price": 75000, "ends_at": "2026-06-10T19:52:00Z", "dealer": "Bring a Trailer", "fmv": 125000, "fmv_low": 120000, "fmv_high": 142000, "conf": "HIGH"}, {"id": 13798, "status": "active", "price": 80250, "ends_at": "2026-06-10T18:59:17Z", "dealer": "pcarmarket", "fmv": 277000, "fmv_low": 260000, "fmv_high": 305000, "conf": "HIGH"}, {"id": 13799, "status": "active", "price": 40000, "ends_at": "2026-06-10T18:59:17Z", "dealer": "pcarmarket", "fmv": 157000, "fmv_low": 119000, "fmv_high": 180000, "conf": "HIGH"}, {"id": 13812, "status": "active", "price": 0, "ends_at": "2026-06-10T18:59:17Z", "dealer": "pcarmarket", "fmv": 0, "fmv_low": 0, "fmv_high": 0, "conf": "NONE"}, {"id": 13816, "status": "active", "price": 5500, "ends_at": "2026-06-10T20:37:00Z", "dealer": "Bring a Trailer", "fmv": 27750, "fmv_low": 22000, "fmv_high": 34000, "conf": "HIGH"}, {"id": 13822, "status": "active", "price": 6800, "ends_at": "2026-06-10T17:34:07Z", "dealer": "Cars and Bids", "fmv": 52000, "fmv_low": 41911, "fmv_high": 63500, "conf": "HIGH"}, {"id": 13827, "status": "active", "price": 40000, "ends_at": "2026-06-10T17:34:07Z", "dealer": "Cars and Bids", "fmv": 73000, "fmv_low": 58920, "fmv_high": 93000, "conf": "HIGH"}, {"id": 13844, "status": "active", "price": 25250, "ends_at": "2026-06-10T18:59:17Z", "dealer": "pcarmarket", "fmv": 0, "fmv_low": 0, "fmv_high": 0, "conf": "NONE"}, {"id": 13892, "status": "active", "price": 0, "ends_at": "2026-06-08T18:39:49Z", "dealer": "pcarmarket", "fmv": 0, "fmv_low": 0, "fmv_high": 0, "conf": "NONE"}, {"id": 13957, "status": "active", "price": 3100, "ends_at": "2026-06-11T18:14:00Z", "dealer": "Bring a Trailer", "fmv": 14000, "fmv_low": 11400, "fmv_high": 17000, "conf": "MEDIUM"}, {"id": 13963, "status": "active", "price": 20510, "ends_at": "2026-06-11T17:34:07Z", "dealer": "Cars and Bids", "fmv": 40750, "fmv_low": 34750, "fmv_high": 47250, "conf": "MEDIUM"}, {"id": 13966, "status": "active", "price": 29250, "ends_at": "2026-06-05T20:22:00Z", "dealer": "Bring a Trailer", "fmv": 27750, "fmv_low": 22000, "fmv_high": 34000, "conf": "HIGH"}, {"id": 13967, "status": "active", "price": 3500, "ends_at": "2026-06-10T19:22:00Z", "dealer": "Bring a Trailer", "fmv": 16000, "fmv_low": 13000, "fmv_high": 19000, "conf": "HIGH"}, {"id": 13968, "status": "active", "price": 10250, "ends_at": "2026-06-11T17:34:07Z", "dealer": "Cars and Bids", "fmv": 27750, "fmv_low": 22000, "fmv_high": 34000, "conf": "HIGH"}, {"id": 13973, "status": "active", "price": 105000, "ends_at": "2026-06-08T17:22:00Z", "dealer": "Bring a Trailer", "fmv": 170000, "fmv_low": 133000, "fmv_high": 216000, "conf": "HIGH"}, {"id": 13975, "status": "active", "price": 47777, "ends_at": "2026-06-11T17:34:07Z", "dealer": "Cars and Bids", "fmv": 57000, "fmv_low": 51000, "fmv_high": 65000, "conf": "HIGH"}, {"id": 13977, "status": "active", "price": 41500, "ends_at": "2026-06-05T17:43:00Z", "dealer": "Bring a Trailer", "fmv": 52000, "fmv_low": 41911, "fmv_high": 63500, "conf": "HIGH"}, {"id": 13978, "status": "active", "price": 247000, "ends_at": "2026-06-05T19:17:00Z", "dealer": "Bring a Trailer", "fmv": 236000, "fmv_low": 222000, "fmv_high": 264000, "conf": "HIGH"}, {"id": 13979, "status": "active", "price": 50000, "ends_at": "2026-06-11T20:54:00Z", "dealer": "Bring a Trailer", "fmv": 121000, "fmv_low": 80750, "fmv_high": 188000, "conf": "MEDIUM"}, {"id": 13980, "status": "active", "price": 350000, "ends_at": "2026-06-12T17:15:00Z", "dealer": "Bring a Trailer", "fmv": 443000, "fmv_low": 420000, "fmv_high": 528000, "conf": "HIGH"}, {"id": 13982, "status": "active", "price": 19987, "ends_at": "2026-06-11T17:34:07Z", "dealer": "Cars and Bids", "fmv": 70000, "fmv_low": 68000, "fmv_high": 83987, "conf": "HIGH"}, {"id": 13993, "status": "active", "price": 10000, "ends_at": "2026-06-11T19:24:00Z", "dealer": "Bring a Trailer", "fmv": 78500, "fmv_low": 72000, "fmv_high": 91000, "conf": "HIGH"}, {"id": 13995, "status": "active", "price": 71000, "ends_at": "2026-06-11T17:34:07Z", "dealer": "Cars and Bids", "fmv": 97500, "fmv_low": 90500, "fmv_high": 104000, "conf": "HIGH"}, {"id": 13997, "status": "active", "price": 0, "ends_at": "2026-06-11T18:59:21Z", "dealer": "pcarmarket", "fmv": 0, "fmv_low": 0, "fmv_high": 0, "conf": "NONE"}, {"id": 13998, "status": "active", "price": 0, "ends_at": "2026-06-11T18:59:21Z", "dealer": "pcarmarket", "fmv": 0, "fmv_low": 0, "fmv_high": 0, "conf": "NONE"}, {"id": 14078, "status": "active", "price": 20000, "ends_at": "2026-06-12T17:32:00Z", "dealer": "Bring a Trailer", "fmv": 165000, "fmv_low": 130000, "fmv_high": 200000, "conf": "HIGH"}, {"id": 14090, "status": "active", "price": 25000, "ends_at": "2026-06-12T19:20:00Z", "dealer": "Bring a Trailer", "fmv": 125000, "fmv_low": 120000, "fmv_high": 142000, "conf": "HIGH"}, {"id": 14093, "status": "active", "price": 15000, "ends_at": "2026-06-12T17:49:00Z", "dealer": "Bring a Trailer", "fmv": 40750, "fmv_low": 34750, "fmv_high": 47250, "conf": "MEDIUM"}, {"id": 14106, "status": "active", "price": 50000, "ends_at": "2026-06-12T17:34:07Z", "dealer": "Cars and Bids", "fmv": 236000, "fmv_low": 222000, "fmv_high": 264000, "conf": "HIGH"}], "ended_ids": [12892, 12902, 13962, 13659, 12901, 12894, 12890, 12893, 13815, 13774, 13797, 12884, 13513, 12882, 13643, 13769, 13666, 13642, 12856, 12888, 12881, 12850, 12857, 13512, 13525, 12848, 12835, 12843, 12812, 13665, 12891, 12885, 13422, 13511, 12722, 12719, 12714, 12732, 12847, 12702, 12855, 12710, 13299, 13638, 13510, 12903, 12867, 12621, 12618, 12589, 12600, 12899, 12687, 13421, 12887, 12898, 12900, 12689, 12883, 11276, 11273, 11272, 11271, 11270, 11269, 1629, 12590, 12392, 12278, 12277, 12897, 12886, 12254, 12889, 12854, 12250, 12266, 12617, 12236, 12595]}